selcuk_serverless_aws_lambda_sdk/__init__.py
selcuk_serverless_aws_lambda_sdk/base.py
selcuk_serverless_aws_lambda_sdk/exceptions.py
selcuk_serverless_aws_lambda_sdk/instrument/__init__.py
selcuk_serverless_aws_lambda_sdk/internal_extension/__init__.py
selcuk_serverless_aws_lambda_sdk/internal_extension/base.py
selcuk_serverless_aws_lambda_sdk/internal_extension/exec_wrapper.py
selcuk_serverless_aws_lambda_sdk/internal_extension/wrapper.py
selcuk_serverless_aws_lambda_sdk/tests/__init__.py
selcuk_serverless_aws_lambda_sdk/tests/example.py
selcuk_serverless_aws_lambda_sdk/tests/test_instrument.py
selcuk_serverless_aws_lambda_sdk/tests/test_internal_extension.py
selcuk_serverless_aws_lambda_sdk-0.0.3.dist-info/METADATA
selcuk_serverless_aws_lambda_sdk-0.0.3.dist-info/WHEEL
selcuk_serverless_aws_lambda_sdk-0.0.3.dist-info/top_level.txt
selcuk_serverless_aws_lambda_sdk-0.0.3.dist-info/RECORD
