Metadata-Version: 2.1
Name: selcuk-serverless-aws-lambda-sdk
Version: 0.0.3
Summary: Serverless  AWS Lambda SDK for Python
Author: selcuk_
Requires-Python: >=3.7
Requires-Dist: selcuk-serverless-sdk
Requires-Dist: selcuk-serverless-sdk-schema
Requires-Dist: strenum (>=0.4.9)
Requires-Dist: typing-extensions (>=4.4)
Provides-Extra: tests
Requires-Dist: black (>=22.12) ; extra == 'tests'
Requires-Dist: pytest (>=7.2) ; extra == 'tests'
Requires-Dist: ruff (>=0.0.199) ; extra == 'tests'
